__init__.py
pyinitgen/__init__.py
pyinitgen/banner.py
pyinitgen/cli.py
pyinitgen/config.py
pyinitgen/ignores.py
pyinitgen-4.0.1.dist-info/METADATA
pyinitgen-4.0.1.dist-info/WHEEL
pyinitgen-4.0.1.dist-info/entry_points.txt
pyinitgen-4.0.1.dist-info/top_level.txt
pyinitgen-4.0.1.dist-info/RECORD
